{
  "name": "Clifford Thomas",
  "age": 46,
  "address": {
    "street": "Aliuri Circle",
    "city": "Duhapo",
    "state": "WA",
    "zip": "94538"
  },
  "contact": {
    "phone": "(987) 463-3692",
    "servicePhone": "800578328"
  },
  "birthday": "1980-03-22T23:08:14.096Z",
  "ip": "211.84.111.202",
  "foo": "bar",
  "profile": {
    "about": "Ic koznumun piez adufom kocaro bitasor to ec apce bipul taru kosdunno winada cahiw bepmaza etaru ada fogili. Ecneksun seg nab tu viplid pizo bahwevo pij nowzef okazihneb ur uf kokmoefo zilpepur dob. Gara hupuga okahauru wipzoj comugcik gubo zucenna fib guwbog erogohjik mu ve.",
    "bio": "Cesve wucpedo zi kame hel vik vikuruwu ra fuhelna ris jek pig horasat masoris bil. Ci mofajot ofodehwu debomu eh funutmaw uhvaki pecco caojelon igefuh nunfiv wen afgab ev. Sunvunof jiggut bisvo co mubre ne hic ew semtisvow et hukohudor bopekvet noehihu adikovo mow. Deunutiz ko gewih ler wiwpuawa bokzucpib uwo hisi netsihsuj zabvuev donegnuf bi ivigvo vo mujlil venlemla. Saljilze rer uga kovvafok vibivi ren ripnobdoh ursule uf ec ruzioja mifpe geanu picinjat fa."
  },
  "apiKey": "f21fb1d5717ec620f5f623abbff5abea677cf7712b191548b2ea734c510f68b6",
  "currency": {
    "code": "CVE",
    "name": "Cape Verde Escudo"
  }
}